dsn_redis/__init__.py
dsn_redis/builders.py
dsn_redis/prototypes.py
dsn_redis_wrapper/__init__.py
dsn_redis_wrapper/builders.py
dsn_redis_wrapper/prototypes.py
dsn_redis_wrapper-1.0.5.dist-info/DESCRIPTION.rst
dsn_redis_wrapper-1.0.5.dist-info/METADATA
dsn_redis_wrapper-1.0.5.dist-info/RECORD
dsn_redis_wrapper-1.0.5.dist-info/WHEEL
dsn_redis_wrapper-1.0.5.dist-info/metadata.json
dsn_redis_wrapper-1.0.5.dist-info/top_level.txt
