Metadata-Version: 2.0
Name: dsn-redis-wrapper
Version: 1.0.5
Summary: A simple and lightweight wrapper for redis
Home-page: https://github.com/desean/redis-wrapper
Author: ['desean']
Author-email: ['desean66@outlook.com']
License: MIT
Platform: UNKNOWN
Classifier: Development Status :: 4 - Beta
Classifier: License :: OSI Approved :: MIT License
Classifier: Programming Language :: Python :: 3.6
Classifier: Intended Audience :: Developers
Classifier: Topic :: Internet :: WWW/HTTP
Classifier: Topic :: Software Development :: Libraries :: Python Modules
Requires-Dist: hiredis (>=0.2.0)
Requires-Dist: redis (>=2.10.5)
Requires-Dist: setuptools
